shldn/__init__.py
shldn/__version__.py
shldn/cooper.py
shldn/leonard.py
shldn/visitors/__init__.py
shldn/visitors/divisitor.py
shldn-1.2.1.dist-info/METADATA
shldn-1.2.1.dist-info/RECORD
shldn-1.2.1.dist-info/WHEEL
shldn-1.2.1.dist-info/entry_points.txt
shldn-1.2.1.dist-info/top_level.txt
