Metadata-Version: 2.1
Name: shldn
Version: 1.2.1
Summary: Find divisions in Python code
Home-page: https://github.com/NablaZeroLabs/shldn
Author: Nabla Zero Labs
Author-email: pablo.ordorica@nablazerolabs.com
Maintainer: Pablo Ordorica Wiener
License: MIT
Platform: UNKNOWN
Classifier: Programming Language :: Python :: 3.7
Classifier: License :: OSI Approved :: MIT License
Classifier: Operating System :: OS Independent
Requires-Python: >=3.6.0
